literature_mcp_pro/__init__.py
literature_mcp_pro/cli.py
literature_mcp_pro/config.py
literature_mcp_pro/ai/analyzer.py
literature_mcp_pro/ai/recommender.py
literature_mcp_pro/ai/semantic_search.py
literature_mcp_pro/ai/summarizer.py
literature_mcp_pro/connectors/__init__.py
literature_mcp_pro/connectors/arxiv.py
literature_mcp_pro/connectors/crossref.py
literature_mcp_pro/connectors/europepmc.py
literature_mcp_pro/connectors/pubmed.py
literature_mcp_pro/connectors/scholar.py
literature_mcp_pro/models/__init__.py
literature_mcp_pro/tools/__init__.py
literature_mcp_pro/tools/analysis.py
literature_mcp_pro/tools/search.py
literature_mcp_pro-0.1.1.dist-info/METADATA
literature_mcp_pro-0.1.1.dist-info/WHEEL
literature_mcp_pro-0.1.1.dist-info/entry_points.txt
literature_mcp_pro-0.1.1.dist-info/RECORD
