Metadata-Version: 2.4
Name: literature-mcp-pro
Version: 0.1.1
Summary: Advanced Literature Management MCP Server with AI-powered analysis
Author-email: Your Name <your.email@example.com>
License: MIT
Keywords: ai-analysis,arxiv,literature,mcp,pubmed,research
Classifier: Development Status :: 4 - Beta
Classifier: Intended Audience :: Science/Research
Classifier: License :: OSI Approved :: MIT License
Classifier: Programming Language :: Python :: 3.10
Classifier: Programming Language :: Python :: 3.11
Classifier: Programming Language :: Python :: 3.12
Requires-Python: >=3.10
Requires-Dist: aiohttp>=3.9.0
Requires-Dist: aiosqlite>=0.19.0
Requires-Dist: beautifulsoup4>=4.12.0
Requires-Dist: httpx>=0.25.0
Requires-Dist: lxml>=5.0.0
Requires-Dist: mcp>=1.0.0
Requires-Dist: networkx>=3.2.0
Requires-Dist: numpy>=1.24.0
Requires-Dist: orjson>=3.9.0
Requires-Dist: pandas>=2.0.0
Requires-Dist: plotly>=5.18.0
Requires-Dist: pydantic>=2.5.0
Requires-Dist: python-dateutil>=2.8.0
Requires-Dist: python-dotenv>=1.0.0
Requires-Dist: tenacity>=8.2.0
Requires-Dist: xmltodict>=0.13.0
Provides-Extra: dev
Requires-Dist: black>=23.0.0; extra == 'dev'
Requires-Dist: mypy>=1.7.0; extra == 'dev'
Requires-Dist: pytest-asyncio>=0.21.0; extra == 'dev'
Requires-Dist: pytest>=7.4.0; extra == 'dev'
Requires-Dist: ruff>=0.1.0; extra == 'dev'
